<?xml version="1.0" encoding="utf-8" ?>
<data>
    <data>
        <item>
            <id>1</id>
            <name>aaa</name>
            <visits>21</visits>
        </item>
        <item>
            <id>2</id>
            <name>aab</name>
            <visits>12</visits>
        </item>
        <item>
            <id>3</id>
            <name>aba</name>
            <visits>8</visits>
        </item>
        <item>
            <id>4</id>
            <name>baa</name>
            <visits>22</visits>
        </item>
        <item>
            <id>5</id>
            <name>bbb</name>
            <visits>52</visits>
        </item>
    </data>
</data>