<?xml version="1.0" encoding="utf-8" ?>
<data>
    <data>
        <item>
            <name>Referrals from search engines</name>
            <visits>1105</visits>
        </item>
        <item>
            <name>Direct entries</name>
            <visits>53</visits>
        </item>
        <item>
            <name>Website link clicks</name>
            <visits>2100</visits>
        </item>
        <item>
            <name>Ad clicks</name>
            <visits>2690</visits>
        </item>
    </data>
    <totals>
        <visits>6620</visits>
    </totals>
</data>
